cir_model/__init__.py
cir_model/cir_model.py
cir_model-0.2.0.dist-info/LICENSE.txt
cir_model-0.2.0.dist-info/METADATA
cir_model-0.2.0.dist-info/WHEEL
cir_model-0.2.0.dist-info/top_level.txt
cir_model-0.2.0.dist-info/RECORD
