Metadata-Version: 2.1
Name: cir-model
Version: 0.2.0
Summary: Centered Isotonic Regression (CIR) is a strictly monotonic, nonparametric regression model
License: BSD 3-Clause License
Project-URL: GitHub, https://github.com/mathijs02/cir-model
Requires-Python: >=3.5
License-File: LICENSE.txt
Requires-Dist: numpy
Requires-Dist: scikit-learn (>=0.14)
